dhl_sdk/__init__.py
dhl_sdk/_constants.py
dhl_sdk/_input_processing.py
dhl_sdk/_spectra_utils.py
dhl_sdk/_utils.py
dhl_sdk/authentication.py
dhl_sdk/client.py
dhl_sdk/crud.py
dhl_sdk/db_entities.py
dhl_sdk/entities.py
dhl_sdk/exceptions.py
dhl_sdk/importers.py
dhl_sdk/validators.py
datahowlab_sdk-0.3.2.dist-info/LICENSE
datahowlab_sdk-0.3.2.dist-info/METADATA
datahowlab_sdk-0.3.2.dist-info/WHEEL
datahowlab_sdk-0.3.2.dist-info/RECORD
