Metadata-Version: 2.3
Name: datahowlab-sdk
Version: 0.3.2
Summary: The DataHowLab SDK for Python
License: Apache-2.0
Author: DataHow
Author-email: feedback@datahow.ch
Requires-Python: >=3.9,<3.13
Classifier: License :: OSI Approved :: Apache Software License
Classifier: Programming Language :: Python :: 3
Classifier: Programming Language :: Python :: 3.9
Classifier: Programming Language :: Python :: 3.10
Classifier: Programming Language :: Python :: 3.11
Classifier: Programming Language :: Python :: 3.12
Requires-Dist: numpy (>=1.26.1,<2.0.0)
Requires-Dist: pydantic (>=2.4.2,<3.0.0)
Requires-Dist: requests (>=2.31.0,<3.0.0)
Project-URL: Homepage, https://datahow.ch/
Project-URL: Source, https://github.com/DataHow/datahowlab-sdk-python
